{
  "connection": "default",
  "collectionName": "femaleapparel",
  "info": {
    "name": "femaleapparel",
    "description": ""
  },
  "options": {
    "timestamps": [
      "createdAt",
      "updatedAt"
    ]
  },
  "attributes": {
    "Name": {
      "type": "string"
    },
    "Price": {
      "type": "integer"
    },
    "Min_Level": {
      "type": "integer"
    },
    "Retail_url": {
      "type": "string"
    },
    "Apple": {
      "model": "file",
      "via": "related",
      "plugin": "upload"
    },
    "Banana": {
      "model": "file",
      "via": "related",
      "plugin": "upload"
    },
    "Pear": {
      "model": "file",
      "via": "related",
      "plugin": "upload"
    },
    "Hour_Glass": {
      "model": "file",
      "via": "related",
      "plugin": "upload"
    },
    "Preview_Image": {
      "collection": "file",
      "via": "related",
      "plugin": "upload"
    },
    "Brand": {
      "model": "businesses"
    },
    "subcategory": {
      "model": "subcategoryapparel"
    },
    "topcategory": {
      "model": "topcategoryapparels"
    }
  }
}