{
  "connection": "default",
  "collectionName": "businesses",
  "info": {
    "name": "businesses",
    "description": ""
  },
  "options": {
    "timestamps": [
      "createdAt",
      "updatedAt"
    ]
  },
  "attributes": {
    "BusinessName": {
      "type": "string"
    },
    "Logo": {
      "model": "file",
      "via": "related",
      "plugin": "upload"
    },
    "email": {
      "type": "email"
    },
    "BusinessAddress": {
      "type": "string"
    },
    "LocationNumber": {
      "type": "integer"
    },
    "website": {
      "type": "string"
    },
    "SupervisorName": {
      "type": "string"
    },
    "PhoneNumber": {
      "type": "integer"
    },
    "City": {
      "type": "string"
    },
    "State": {
      "type": "string"
    },
    "ZipCode": {
      "type": "string"
    },
    "Longitude": {
      "type": "float"
    },
    "latitude": {
      "type": "float"
    },
    "QR_Code": {
      "model": "file",
      "via": "related",
      "plugin": "upload"
    },
    "Geolocation_Polygon": {
      "type": "json"
    },
    "Business_TopCategory": {
      "model": "topcategoryoffers"
    },
    "Business_SubCategory": {
      "model": "subcategoryoffers"
    },
    "Location_Bonus": {
      "type": "integer"
    },
    "workoutypes": {
      "collection": "workoutypes",
      "via": "businesses",
      "dominant": true
    },
    "Business_Picture": {
      "model": "file",
      "via": "related",
      "plugin": "upload"
    },
    "Clothing_Brand": {
      "type": "boolean"
    }
  }
}